setup.py
django_readwrite/__init__.py
django_readwrite/connection.py
django_readwrite/cursors.py
django_readwrite/decorators.py
django_readwrite/middleware.py
django_readwrite/models.py
django_readwrite/patches.py
django_readwrite/pool.py
django_readwrite/readonly.py
django_readwrite/settings.py
django_readwrite/signals.py
django_readwrite/tests.py
django_readwrite/views.py
django_readwrite.egg-info/PKG-INFO
django_readwrite.egg-info/SOURCES.txt
django_readwrite.egg-info/dependency_links.txt
django_readwrite.egg-info/requires.txt
django_readwrite.egg-info/top_level.txt