Metadata-Version: 1.0
Name: django-readwrite
Version: 0.0.1
Summary: Read/write database splitting for Django, based on the HTTP request method.
Home-page: https://github.com/apn-online/django-readwrite
Author: Raymond Butcher
Author-email: randomy@gmail.com
License: MIT
Platform: UNKNOWN
